sqlite_diffable/__init__.py
sqlite_diffable/cli.py
sqlite_diffable-0.6.dist-info/licenses/LICENSE
sqlite_diffable-0.6.dist-info/METADATA
sqlite_diffable-0.6.dist-info/WHEEL
sqlite_diffable-0.6.dist-info/entry_points.txt
sqlite_diffable-0.6.dist-info/top_level.txt
sqlite_diffable-0.6.dist-info/RECORD
