Metadata-Version: 2.4
Name: sqlite-diffable
Version: 0.6
Summary: Tools for dumping/loading a SQLite database to diffable directory structure
Author: Simon Willison
License-Expression: Apache-2.0
Project-URL: Homepage, https://github.com/simonw/sqlite-diffable
Project-URL: Changelog, https://github.com/simonw/sqlite-diffable/releases
Project-URL: Issues, https://github.com/simonw/sqlite-diffable/issues
Project-URL: CI, https://github.com/simonw/sqlite-diffable/actions
Requires-Python: >=3.9
License-File: LICENSE
Requires-Dist: click
Requires-Dist: sqlite-utils
Provides-Extra: test
Requires-Dist: pytest; extra == "test"
Requires-Dist: black; extra == "test"
Dynamic: license-file
